{
"matchDate" : "Fri Mar 22 02:03:16 2019",
"gameDuration": 2422,
"runTime": 420,
"destroyedBuildings": ["npc_dota_badguys_tower1_top", "npc_dota_badguys_tower1_mid", "npc_dota_goodguys_tower1_bot", "npc_dota_badguys_tower2_top", "npc_dota_badguys_tower1_bot", "npc_dota_badguys_tower2_bot", "npc_dota_badguys_tower2_mid", "npc_dota_badguys_tower3_top", "npc_dota_goodguys_tower1_mid", "npc_dota_badguys_tower3_bot", "npc_dota_badguys_range_rax_bot", "npc_dota_badguys_melee_rax_bot", "npc_dota_goodguys_tower2_mid", "npc_dota_badguys_range_rax_top", "npc_dota_badguys_melee_rax_top", "npc_dota_badguys_tower3_mid", "npc_dota_badguys_range_rax_mid", "npc_dota_badguys_melee_rax_mid", "npc_dota_badguys_tower4", "npc_dota_badguys_tower4"],
"winner" : "goodguys",
"numPlayersGood" : 5,
"numPlayersBad" : 5,
"goodguys" : {
	"npc_dota_hero_bane(3)" : {
		"items": [170, 63, 152, 172, 75, 94, 2, 16, 0],
		"lastHit": 57,
		"deny": 17,
		"claimedMiss": 4,
		"claimedDeny": 1,
		"miss": 45,
		"level": 18,
		"gold": 192,
		"kill": 3,
		"death": 12,
		"assist": 13,
		"actualPlayerDamage": 10835,
		"actualBuildingDamage": 0,
		"actualHealing": 0,
		"scaledPlayerDamage": 6998,
		"scaledBuildingDamage": 0,
		"xpPerMin": 286,
		"goldPerMin": 382,
		"claimedFarm": 3863,
		"supportGold": 0
	},
	"npc_dota_hero_chaos_knight(81)" : {
		"items": [116, 50, 148, 51, 3, 140, 0, 36, 25],
		"lastHit": 98,
		"deny": 5,
		"claimedMiss": 54,
		"claimedDeny": 2,
		"miss": 17,
		"level": 20,
		"gold": 179,
		"kill": 8,
		"death": 5,
		"assist": 16,
		"actualPlayerDamage": 19555,
		"actualBuildingDamage": 767,
		"actualHealing": 0,
		"scaledPlayerDamage": 13363,
		"scaledBuildingDamage": 433,
		"xpPerMin": 328,
		"goldPerMin": 445,
		"claimedFarm": 6819,
		"supportGold": 50
	},
	"npc_dota_hero_juggernaut(8)" : {
		"items": [121, 1, 180, 0, 0, 0, 0, 0, 0],
		"lastHit": 65,
		"deny": 2,
		"claimedMiss": 38,
		"claimedDeny": 2,
		"miss": 21,
		"level": 19,
		"gold": 1501,
		"kill": 8,
		"death": 9,
		"assist": 12,
		"actualPlayerDamage": 28722,
		"actualBuildingDamage": 55,
		"actualHealing": 0,
		"scaledPlayerDamage": 15228,
		"scaledBuildingDamage": 23,
		"xpPerMin": 285,
		"goldPerMin": 418,
		"claimedFarm": 5055,
		"supportGold": 0
	},
	"npc_dota_hero_lich(31)" : {
		"items": [42, 180, 1, 100, 92, 21, 36, 0, 0],
		"lastHit": 54,
		"deny": 12,
		"claimedMiss": 60,
		"claimedDeny": 10,
		"miss": 26,
		"level": 19,
		"gold": 366,
		"kill": 4,
		"death": 10,
		"assist": 14,
		"actualPlayerDamage": 17215,
		"actualBuildingDamage": 378,
		"actualHealing": 1491,
		"scaledPlayerDamage": 9558,
		"scaledBuildingDamage": 196,
		"xpPerMin": 295,
		"goldPerMin": 416,
		"claimedFarm": 5659,
		"supportGold": 1500
	},
	"npc_dota_hero_ogre_magi(84)" : {
		"items": [41, 116, 168, 170, 29, 149, 36, 2, 18],
		"lastHit": 144,
		"deny": 26,
		"claimedMiss": 30,
		"claimedDeny": 2,
		"miss": 25,
		"level": 23,
		"gold": 1309,
		"kill": 14,
		"death": 8,
		"assist": 11,
		"actualPlayerDamage": 39796,
		"actualBuildingDamage": 128,
		"actualHealing": 0,
		"scaledPlayerDamage": 22491,
		"scaledBuildingDamage": 47,
		"xpPerMin": 424,
		"goldPerMin": 568,
		"claimedFarm": 8373,
		"supportGold": 0
	}},
"badguys" : {
	"npc_dota_hero_drow_ranger(6)" : {
		"items": [232, 254, 36, 180, 0, 0, 0, 0, 0],
		"lastHit": 66,
		"deny": 2,
		"claimedMiss": 29,
		"claimedDeny": 0,
		"miss": 32,
		"level": 22,
		"gold": 5179,
		"kill": 7,
		"death": 9,
		"assist": 14,
		"actualPlayerDamage": 17588,
		"actualBuildingDamage": 1889,
		"actualHealing": 0,
		"scaledPlayerDamage": 14156,
		"scaledBuildingDamage": 1041,
		"xpPerMin": 333,
		"goldPerMin": 538,
		"claimedFarm": 5566,
		"supportGold": 50
	},
	"npc_dota_hero_kunkka(23)" : {
		"items": [63, 252, 147, 112, 0, 0, 0, 0, 0],
		"lastHit": 125,
		"deny": 13,
		"claimedMiss": 24,
		"claimedDeny": 0,
		"miss": 12,
		"level": 23,
		"gold": 1425,
		"kill": 11,
		"death": 7,
		"assist": 15,
		"actualPlayerDamage": 25814,
		"actualBuildingDamage": 4417,
		"actualHealing": 0,
		"scaledPlayerDamage": 19800,
		"scaledBuildingDamage": 2206,
		"xpPerMin": 436,
		"goldPerMin": 573,
		"claimedFarm": 6991,
		"supportGold": 0
	},
	"npc_dota_hero_zuus(22)" : {
		"items": [50, 147, 11, 36, 166, 0, 0, 0, 0],
		"lastHit": 148,
		"deny": 3,
		"claimedMiss": 35,
		"claimedDeny": 0,
		"miss": 14,
		"level": 23,
		"gold": 7048,
		"kill": 7,
		"death": 5,
		"assist": 14,
		"actualPlayerDamage": 19742,
		"actualBuildingDamage": 5895,
		"actualHealing": 10426,
		"scaledPlayerDamage": 13312,
		"scaledBuildingDamage": 3030,
		"xpPerMin": 424,
		"goldPerMin": 602,
		"claimedFarm": 8143,
		"supportGold": 0
	},
	"npc_dota_hero_earthshaker(7)" : {
		"items": [214, 254, 108, 102, 0, 0, 0, 0, 0],
		"lastHit": 113,
		"deny": 10,
		"claimedMiss": 41,
		"claimedDeny": 2,
		"miss": 34,
		"level": 22,
		"gold": 4125,
		"kill": 4,
		"death": 9,
		"assist": 13,
		"actualPlayerDamage": 24403,
		"actualBuildingDamage": 5056,
		"actualHealing": 0,
		"scaledPlayerDamage": 15891,
		"scaledBuildingDamage": 2814,
		"xpPerMin": 379,
		"goldPerMin": 533,
		"claimedFarm": 8420,
		"supportGold": 0
	},
	"npc_dota_hero_nevermore(11)" : {
		"items": [58, 180, 24, 259, 102, 0, 0, 0, 0],
		"lastHit": 103,
		"deny": 4,
		"claimedMiss": 63,
		"claimedDeny": 4,
		"miss": 29,
		"level": 22,
		"gold": 3198,
		"kill": 14,
		"death": 8,
		"assist": 6,
		"actualPlayerDamage": 24579,
		"actualBuildingDamage": 703,
		"actualHealing": 0,
		"scaledPlayerDamage": 18845,
		"scaledBuildingDamage": 368,
		"xpPerMin": 408,
		"goldPerMin": 547,
		"claimedFarm": 8707,
		"supportGold": 0
	}
}}
