{
"matchDate" : "Fri Mar 22 02:02:49 2019",
"gameDuration": 1843,
"runTime": 322,
"destroyedBuildings": ["npc_dota_badguys_tower1_top", "npc_dota_goodguys_tower1_top", "npc_dota_goodguys_tower1_mid", "npc_dota_badguys_tower1_bot", "npc_dota_badguys_tower1_mid", "npc_dota_badguys_tower2_top", "npc_dota_badguys_tower2_bot", "npc_dota_badguys_tower2_mid", "npc_dota_badguys_tower3_mid", "npc_dota_badguys_range_rax_mid", "npc_dota_badguys_melee_rax_mid", "npc_dota_badguys_tower3_bot", "npc_dota_badguys_range_rax_bot", "npc_dota_badguys_melee_rax_bot", "npc_dota_badguys_tower4", "npc_dota_badguys_tower4"],
"winner" : "goodguys",
"numPlayersGood" : 5,
"numPlayersBad" : 5,
"goodguys" : {
	"npc_dota_hero_bane(3)" : {
		"items": [88, 29, 215, 172, 75, 18, 16, 2, 0],
		"lastHit": 34,
		"deny": 10,
		"claimedMiss": 2,
		"claimedDeny": 1,
		"miss": 35,
		"level": 12,
		"gold": 40,
		"kill": 4,
		"death": 9,
		"assist": 5,
		"actualPlayerDamage": 7047,
		"actualBuildingDamage": 134,
		"actualHealing": 0,
		"scaledPlayerDamage": 6554,
		"scaledBuildingDamage": 57,
		"xpPerMin": 209,
		"goldPerMin": 258,
		"claimedFarm": 2712,
		"supportGold": 0
	},
	"npc_dota_hero_chaos_knight(81)" : {
		"items": [185, 50, 38, 36, 3, 25, 0, 0, 0],
		"lastHit": 42,
		"deny": 8,
		"claimedMiss": 38,
		"claimedDeny": 2,
		"miss": 12,
		"level": 11,
		"gold": 54,
		"kill": 2,
		"death": 12,
		"assist": 8,
		"actualPlayerDamage": 8841,
		"actualBuildingDamage": 388,
		"actualHealing": 0,
		"scaledPlayerDamage": 6468,
		"scaledBuildingDamage": 204,
		"xpPerMin": 213,
		"goldPerMin": 228,
		"claimedFarm": 3591,
		"supportGold": 50
	},
	"npc_dota_hero_juggernaut(8)" : {
		"items": [69, 1, 180, 61, 0, 0, 0, 0, 0],
		"lastHit": 39,
		"deny": 7,
		"claimedMiss": 40,
		"claimedDeny": 4,
		"miss": 12,
		"level": 14,
		"gold": 281,
		"kill": 5,
		"death": 9,
		"assist": 9,
		"actualPlayerDamage": 13844,
		"actualBuildingDamage": 85,
		"actualHealing": 0,
		"scaledPlayerDamage": 10647,
		"scaledBuildingDamage": 35,
		"xpPerMin": 249,
		"goldPerMin": 328,
		"claimedFarm": 3702,
		"supportGold": 0
	},
	"npc_dota_hero_lich(31)" : {
		"items": [42, 180, 38, 36, 0, 0, 0, 0, 0],
		"lastHit": 35,
		"deny": 11,
		"claimedMiss": 20,
		"claimedDeny": 3,
		"miss": 22,
		"level": 10,
		"gold": 1550,
		"kill": 1,
		"death": 16,
		"assist": 4,
		"actualPlayerDamage": 8571,
		"actualBuildingDamage": 321,
		"actualHealing": 0,
		"scaledPlayerDamage": 5176,
		"scaledBuildingDamage": 165,
		"xpPerMin": 195,
		"goldPerMin": 185,
		"claimedFarm": 2656,
		"supportGold": 1200
	},
	"npc_dota_hero_ogre_magi(84)" : {
		"items": [41, 29, 8, 170, 18, 21, 2, 36, 0],
		"lastHit": 83,
		"deny": 29,
		"claimedMiss": 36,
		"claimedDeny": 4,
		"miss": 27,
		"level": 14,
		"gold": 73,
		"kill": 4,
		"death": 9,
		"assist": 1,
		"actualPlayerDamage": 15133,
		"actualBuildingDamage": 655,
		"actualHealing": 0,
		"scaledPlayerDamage": 11165,
		"scaledBuildingDamage": 365,
		"xpPerMin": 266,
		"goldPerMin": 332,
		"claimedFarm": 6083,
		"supportGold": 0
	}},
"badguys" : {
	"npc_dota_hero_drow_ranger(6)" : {
		"items": [180, 232, 36, 254, 58, 0, 0, 0, 0],
		"lastHit": 54,
		"deny": 10,
		"claimedMiss": 18,
		"claimedDeny": 0,
		"miss": 29,
		"level": 21,
		"gold": 2373,
		"kill": 6,
		"death": 3,
		"assist": 31,
		"actualPlayerDamage": 17150,
		"actualBuildingDamage": 1477,
		"actualHealing": 0,
		"scaledPlayerDamage": 14495,
		"scaledBuildingDamage": 844,
		"xpPerMin": 380,
		"goldPerMin": 636,
		"claimedFarm": 4288,
		"supportGold": 50
	},
	"npc_dota_hero_kunkka(23)" : {
		"items": [24, 63, 252, 112, 0, 0, 0, 0, 0],
		"lastHit": 85,
		"deny": 4,
		"claimedMiss": 19,
		"claimedDeny": 0,
		"miss": 17,
		"level": 20,
		"gold": 1494,
		"kill": 21,
		"death": 2,
		"assist": 18,
		"actualPlayerDamage": 26995,
		"actualBuildingDamage": 4671,
		"actualHealing": 0,
		"scaledPlayerDamage": 22778,
		"scaledBuildingDamage": 2656,
		"xpPerMin": 519,
		"goldPerMin": 566,
		"claimedFarm": 4964,
		"supportGold": 0
	},
	"npc_dota_hero_zuus(22)" : {
		"items": [50, 147, 11, 36, 166, 0, 0, 0, 0],
		"lastHit": 75,
		"deny": 8,
		"claimedMiss": 22,
		"claimedDeny": 1,
		"miss": 16,
		"level": 16,
		"gold": 2105,
		"kill": 8,
		"death": 4,
		"assist": 11,
		"actualPlayerDamage": 10925,
		"actualBuildingDamage": 2779,
		"actualHealing": 3706,
		"scaledPlayerDamage": 9055,
		"scaledBuildingDamage": 1554,
		"xpPerMin": 393,
		"goldPerMin": 414,
		"claimedFarm": 4368,
		"supportGold": 0
	},
	"npc_dota_hero_earthshaker(7)" : {
		"items": [254, 214, 108, 102, 0, 0, 0, 0, 0],
		"lastHit": 68,
		"deny": 5,
		"claimedMiss": 38,
		"claimedDeny": 1,
		"miss": 28,
		"level": 20,
		"gold": 2494,
		"kill": 11,
		"death": 6,
		"assist": 10,
		"actualPlayerDamage": 17605,
		"actualBuildingDamage": 3346,
		"actualHealing": 0,
		"scaledPlayerDamage": 14927,
		"scaledBuildingDamage": 1955,
		"xpPerMin": 425,
		"goldPerMin": 569,
		"claimedFarm": 5630,
		"supportGold": 0
	},
	"npc_dota_hero_nevermore(11)" : {
		"items": [58, 180, 0, 259, 102, 0, 0, 0, 0],
		"lastHit": 50,
		"deny": 6,
		"claimedMiss": 39,
		"claimedDeny": 2,
		"miss": 25,
		"level": 18,
		"gold": 1470,
		"kill": 9,
		"death": 2,
		"assist": 20,
		"actualPlayerDamage": 20594,
		"actualBuildingDamage": 1751,
		"actualHealing": 0,
		"scaledPlayerDamage": 17908,
		"scaledBuildingDamage": 871,
		"xpPerMin": 362,
		"goldPerMin": 508,
		"claimedFarm": 4805,
		"supportGold": 0
	}
}}
