{
"matchDate" : "Fri Mar 22 02:03:40 2019",
"gameDuration": 2504,
"runTime": 434,
"destroyedBuildings": ["npc_dota_badguys_tower1_mid", "npc_dota_badguys_tower1_top", "npc_dota_badguys_tower1_bot", "npc_dota_badguys_tower2_top", "npc_dota_badguys_tower2_bot", "npc_dota_badguys_tower2_mid", "npc_dota_goodguys_tower1_mid", "npc_dota_goodguys_tower2_mid", "npc_dota_badguys_tower3_bot", "npc_dota_badguys_range_rax_bot", "npc_dota_goodguys_tower1_bot", "npc_dota_badguys_tower3_top", "npc_dota_badguys_range_rax_top", "npc_dota_badguys_melee_rax_top", "npc_dota_badguys_melee_rax_bot", "npc_dota_badguys_tower4", "npc_dota_badguys_tower3_mid", "npc_dota_badguys_range_rax_mid", "npc_dota_badguys_melee_rax_mid", "npc_dota_badguys_tower4"],
"winner" : "goodguys",
"numPlayersGood" : 5,
"numPlayersBad" : 5,
"goodguys" : {
	"npc_dota_hero_bane(3)" : {
		"items": [29, 152, 88, 75, 18, 172, 2, 16, 0],
		"lastHit": 52,
		"deny": 7,
		"claimedMiss": 6,
		"claimedDeny": 0,
		"miss": 23,
		"level": 18,
		"gold": 87,
		"kill": 5,
		"death": 16,
		"assist": 14,
		"actualPlayerDamage": 11015,
		"actualBuildingDamage": 627,
		"actualHealing": 0,
		"scaledPlayerDamage": 8093,
		"scaledBuildingDamage": 364,
		"xpPerMin": 262,
		"goldPerMin": 362,
		"claimedFarm": 2936,
		"supportGold": 150
	},
	"npc_dota_hero_chaos_knight(81)" : {
		"items": [185, 38, 141, 116, 4, 25, 29, 36, 0],
		"lastHit": 132,
		"deny": 14,
		"claimedMiss": 48,
		"claimedDeny": 4,
		"miss": 16,
		"level": 20,
		"gold": 779,
		"kill": 6,
		"death": 7,
		"assist": 13,
		"actualPlayerDamage": 19740,
		"actualBuildingDamage": 519,
		"actualHealing": 0,
		"scaledPlayerDamage": 12969,
		"scaledBuildingDamage": 307,
		"xpPerMin": 351,
		"goldPerMin": 442,
		"claimedFarm": 7878,
		"supportGold": 50
	},
	"npc_dota_hero_juggernaut(8)" : {
		"items": [121, 1, 180, 0, 0, 0, 0, 0, 0],
		"lastHit": 55,
		"deny": 7,
		"claimedMiss": 36,
		"claimedDeny": 2,
		"miss": 13,
		"level": 25,
		"gold": 5806,
		"kill": 12,
		"death": 7,
		"assist": 13,
		"actualPlayerDamage": 38578,
		"actualBuildingDamage": 350,
		"actualHealing": 0,
		"scaledPlayerDamage": 21045,
		"scaledBuildingDamage": 197,
		"xpPerMin": 364,
		"goldPerMin": 746,
		"claimedFarm": 4394,
		"supportGold": 0
	},
	"npc_dota_hero_lich(31)" : {
		"items": [21, 180, 1, 8, 100, 42, 36, 92, 0],
		"lastHit": 77,
		"deny": 5,
		"claimedMiss": 54,
		"claimedDeny": 3,
		"miss": 22,
		"level": 22,
		"gold": 993,
		"kill": 7,
		"death": 11,
		"assist": 14,
		"actualPlayerDamage": 19928,
		"actualBuildingDamage": 471,
		"actualHealing": 480,
		"scaledPlayerDamage": 12863,
		"scaledBuildingDamage": 250,
		"xpPerMin": 324,
		"goldPerMin": 493,
		"claimedFarm": 6447,
		"supportGold": 675
	},
	"npc_dota_hero_ogre_magi(84)" : {
		"items": [116, 29, 41, 170, 168, 36, 0, 2, 18],
		"lastHit": 133,
		"deny": 27,
		"claimedMiss": 42,
		"claimedDeny": 1,
		"miss": 30,
		"level": 21,
		"gold": 691,
		"kill": 6,
		"death": 12,
		"assist": 9,
		"actualPlayerDamage": 24570,
		"actualBuildingDamage": 364,
		"actualHealing": 0,
		"scaledPlayerDamage": 14820,
		"scaledBuildingDamage": 264,
		"xpPerMin": 352,
		"goldPerMin": 466,
		"claimedFarm": 7951,
		"supportGold": 0
	}},
"badguys" : {
	"npc_dota_hero_drow_ranger(6)" : {
		"items": [180, 232, 36, 254, 58, 0, 0, 0, 0],
		"lastHit": 69,
		"deny": 9,
		"claimedMiss": 27,
		"claimedDeny": 1,
		"miss": 21,
		"level": 19,
		"gold": 2573,
		"kill": 6,
		"death": 8,
		"assist": 16,
		"actualPlayerDamage": 16006,
		"actualBuildingDamage": 1151,
		"actualHealing": 0,
		"scaledPlayerDamage": 12239,
		"scaledBuildingDamage": 599,
		"xpPerMin": 314,
		"goldPerMin": 384,
		"claimedFarm": 4857,
		"supportGold": 50
	},
	"npc_dota_hero_kunkka(23)" : {
		"items": [63, 44, 21, 112, 10, 19, 147, 0, 0],
		"lastHit": 101,
		"deny": 9,
		"claimedMiss": 29,
		"claimedDeny": 0,
		"miss": 27,
		"level": 25,
		"gold": 5180,
		"kill": 20,
		"death": 8,
		"assist": 12,
		"actualPlayerDamage": 32185,
		"actualBuildingDamage": 2667,
		"actualHealing": 0,
		"scaledPlayerDamage": 23657,
		"scaledBuildingDamage": 1265,
		"xpPerMin": 511,
		"goldPerMin": 738,
		"claimedFarm": 6702,
		"supportGold": 0
	},
	"npc_dota_hero_zuus(22)" : {
		"items": [166, 44, 11, 50, 147, 0, 0, 0, 0],
		"lastHit": 128,
		"deny": 4,
		"claimedMiss": 38,
		"claimedDeny": 0,
		"miss": 20,
		"level": 20,
		"gold": 4231,
		"kill": 5,
		"death": 7,
		"assist": 5,
		"actualPlayerDamage": 12616,
		"actualBuildingDamage": 4245,
		"actualHealing": 6235,
		"scaledPlayerDamage": 9069,
		"scaledBuildingDamage": 2245,
		"xpPerMin": 367,
		"goldPerMin": 431,
		"claimedFarm": 8107,
		"supportGold": 0
	},
	"npc_dota_hero_earthshaker(7)" : {
		"items": [214, 254, 42, 44, 102, 108, 0, 0, 0],
		"lastHit": 97,
		"deny": 5,
		"claimedMiss": 48,
		"claimedDeny": 2,
		"miss": 35,
		"level": 21,
		"gold": 2681,
		"kill": 8,
		"death": 11,
		"assist": 7,
		"actualPlayerDamage": 27427,
		"actualBuildingDamage": 1802,
		"actualHealing": 0,
		"scaledPlayerDamage": 19283,
		"scaledBuildingDamage": 1094,
		"xpPerMin": 350,
		"goldPerMin": 455,
		"claimedFarm": 7911,
		"supportGold": 75
	},
	"npc_dota_hero_nevermore(11)" : {
		"items": [58, 259, 0, 180, 102, 0, 0, 0, 0],
		"lastHit": 106,
		"deny": 5,
		"claimedMiss": 72,
		"claimedDeny": 3,
		"miss": 19,
		"level": 24,
		"gold": 5199,
		"kill": 14,
		"death": 6,
		"assist": 11,
		"actualPlayerDamage": 26553,
		"actualBuildingDamage": 1424,
		"actualHealing": 0,
		"scaledPlayerDamage": 20507,
		"scaledBuildingDamage": 752,
		"xpPerMin": 410,
		"goldPerMin": 610,
		"claimedFarm": 8542,
		"supportGold": 0
	}
}}
