{
"matchDate" : "Fri Mar 22 01:50:56 2019",
"gameDuration": 1848,
"runTime": 347,
"destroyedBuildings": ["npc_dota_badguys_tower1_bot", "npc_dota_badguys_tower1_top", "npc_dota_badguys_tower1_mid", "npc_dota_badguys_tower2_bot", "npc_dota_badguys_tower2_top", "npc_dota_badguys_tower2_mid", "npc_dota_badguys_tower3_bot", "npc_dota_badguys_range_rax_bot", "npc_dota_badguys_tower3_mid", "npc_dota_badguys_melee_rax_mid", "npc_dota_badguys_range_rax_mid", "npc_dota_badguys_melee_rax_bot", "npc_dota_badguys_tower3_top", "npc_dota_badguys_melee_rax_top", "npc_dota_badguys_range_rax_top", "npc_dota_badguys_tower4", "npc_dota_badguys_tower4"],
"winner" : "goodguys",
"numPlayersGood" : 5,
"numPlayersBad" : 5,
"goodguys" : {
	"npc_dota_hero_bane(3)" : {
		"items": [172, 42, 88, 29, 75, 18, 16, 2, 0],
		"lastHit": 31,
		"deny": 7,
		"claimedMiss": 0,
		"claimedDeny": 0,
		"miss": 22,
		"level": 12,
		"gold": 648,
		"kill": 1,
		"death": 14,
		"assist": 8,
		"actualPlayerDamage": 5880,
		"actualBuildingDamage": 37,
		"actualHealing": 0,
		"scaledPlayerDamage": 5410,
		"scaledBuildingDamage": 11,
		"xpPerMin": 200,
		"goldPerMin": 248,
		"claimedFarm": 2110,
		"supportGold": 150
	},
	"npc_dota_hero_chaos_knight(81)" : {
		"items": [185, 38, 50, 3, 36, 25, 0, 0, 0],
		"lastHit": 36,
		"deny": 4,
		"claimedMiss": 43,
		"claimedDeny": 4,
		"miss": 7,
		"level": 13,
		"gold": 165,
		"kill": 1,
		"death": 10,
		"assist": 6,
		"actualPlayerDamage": 8375,
		"actualBuildingDamage": 0,
		"actualHealing": 0,
		"scaledPlayerDamage": 5545,
		"scaledBuildingDamage": 0,
		"xpPerMin": 206,
		"goldPerMin": 267,
		"claimedFarm": 3669,
		"supportGold": 50
	},
	"npc_dota_hero_juggernaut(8)" : {
		"items": [69, 1, 180, 61, 0, 0, 0, 0, 0],
		"lastHit": 31,
		"deny": 6,
		"claimedMiss": 24,
		"claimedDeny": 2,
		"miss": 19,
		"level": 13,
		"gold": 141,
		"kill": 5,
		"death": 10,
		"assist": 8,
		"actualPlayerDamage": 19294,
		"actualBuildingDamage": 0,
		"actualHealing": 0,
		"scaledPlayerDamage": 11735,
		"scaledBuildingDamage": 0,
		"xpPerMin": 242,
		"goldPerMin": 296,
		"claimedFarm": 3072,
		"supportGold": 0
	},
	"npc_dota_hero_lich(31)" : {
		"items": [36, 180, 1, 92, 23, 57, 244, 0, 0],
		"lastHit": 62,
		"deny": 8,
		"claimedMiss": 43,
		"claimedDeny": 5,
		"miss": 10,
		"level": 15,
		"gold": 73,
		"kill": 5,
		"death": 10,
		"assist": 6,
		"actualPlayerDamage": 12803,
		"actualBuildingDamage": 0,
		"actualHealing": 825,
		"scaledPlayerDamage": 9141,
		"scaledBuildingDamage": 0,
		"xpPerMin": 270,
		"goldPerMin": 361,
		"claimedFarm": 4577,
		"supportGold": 0
	},
	"npc_dota_hero_ogre_magi(84)" : {
		"items": [36, 29, 41, 170, 21, 18, 2, 0, 0],
		"lastHit": 50,
		"deny": 19,
		"claimedMiss": 24,
		"claimedDeny": 2,
		"miss": 11,
		"level": 13,
		"gold": 107,
		"kill": 5,
		"death": 13,
		"assist": 2,
		"actualPlayerDamage": 11155,
		"actualBuildingDamage": 0,
		"actualHealing": 0,
		"scaledPlayerDamage": 7769,
		"scaledBuildingDamage": 0,
		"xpPerMin": 226,
		"goldPerMin": 268,
		"claimedFarm": 3432,
		"supportGold": 0
	}},
"badguys" : {
	"npc_dota_hero_drow_ranger(6)" : {
		"items": [232, 180, 36, 254, 58, 0, 0, 0, 0],
		"lastHit": 47,
		"deny": 5,
		"claimedMiss": 28,
		"claimedDeny": 0,
		"miss": 27,
		"level": 16,
		"gold": 1382,
		"kill": 6,
		"death": 3,
		"assist": 12,
		"actualPlayerDamage": 11319,
		"actualBuildingDamage": 992,
		"actualHealing": 0,
		"scaledPlayerDamage": 10734,
		"scaledBuildingDamage": 458,
		"xpPerMin": 353,
		"goldPerMin": 411,
		"claimedFarm": 4133,
		"supportGold": 50
	},
	"npc_dota_hero_kunkka(23)" : {
		"items": [63, 44, 252, 112, 0, 0, 0, 0, 0],
		"lastHit": 88,
		"deny": 8,
		"claimedMiss": 22,
		"claimedDeny": 0,
		"miss": 21,
		"level": 21,
		"gold": 5064,
		"kill": 15,
		"death": 3,
		"assist": 14,
		"actualPlayerDamage": 21462,
		"actualBuildingDamage": 5001,
		"actualHealing": 0,
		"scaledPlayerDamage": 19191,
		"scaledBuildingDamage": 2514,
		"xpPerMin": 499,
		"goldPerMin": 639,
		"claimedFarm": 5144,
		"supportGold": 0
	},
	"npc_dota_hero_zuus(22)" : {
		"items": [50, 44, 158, 11, 147, 69, 0, 0, 0],
		"lastHit": 109,
		"deny": 10,
		"claimedMiss": 17,
		"claimedDeny": 0,
		"miss": 12,
		"level": 18,
		"gold": 1693,
		"kill": 17,
		"death": 2,
		"assist": 8,
		"actualPlayerDamage": 20357,
		"actualBuildingDamage": 5589,
		"actualHealing": 4510,
		"scaledPlayerDamage": 17577,
		"scaledBuildingDamage": 2760,
		"xpPerMin": 521,
		"goldPerMin": 479,
		"claimedFarm": 5435,
		"supportGold": 0
	},
	"npc_dota_hero_earthshaker(7)" : {
		"items": [214, 254, 42, 44, 108, 102, 0, 0, 0],
		"lastHit": 55,
		"deny": 5,
		"claimedMiss": 20,
		"claimedDeny": 0,
		"miss": 31,
		"level": 18,
		"gold": 1516,
		"kill": 7,
		"death": 5,
		"assist": 16,
		"actualPlayerDamage": 15115,
		"actualBuildingDamage": 3073,
		"actualHealing": 0,
		"scaledPlayerDamage": 14285,
		"scaledBuildingDamage": 1630,
		"xpPerMin": 394,
		"goldPerMin": 491,
		"claimedFarm": 4495,
		"supportGold": 75
	},
	"npc_dota_hero_nevermore(11)" : {
		"items": [96, 180, 0, 259, 102, 0, 0, 0, 0],
		"lastHit": 89,
		"deny": 7,
		"claimedMiss": 49,
		"claimedDeny": 4,
		"miss": 24,
		"level": 21,
		"gold": 1631,
		"kill": 11,
		"death": 4,
		"assist": 13,
		"actualPlayerDamage": 23581,
		"actualBuildingDamage": 2364,
		"actualHealing": 0,
		"scaledPlayerDamage": 20916,
		"scaledBuildingDamage": 1323,
		"xpPerMin": 472,
		"goldPerMin": 658,
		"claimedFarm": 7039,
		"supportGold": 0
	}
}}
